{
	"cmake" : 
	{
		"generator" : 
		{
			"multiConfig" : false,
			"name" : "MinGW Makefiles"
		},
		"paths" : 
		{
			"cmake" : "C:/Program Files/CMake/bin/cmake.exe",
			"cpack" : "C:/Program Files/CMake/bin/cpack.exe",
			"ctest" : "C:/Program Files/CMake/bin/ctest.exe",
			"root" : "C:/Program Files/CMake/share/cmake-3.26"
		},
		"version" : 
		{
			"isDirty" : false,
			"major" : 3,
			"minor" : 26,
			"patch" : 3,
			"string" : "3.26.3",
			"suffix" : ""
		}
	},
	"objects" : 
	[
		{
			"jsonFile" : "codemodel-v2-656fd20f3c3bde010993.json",
			"kind" : "codemodel",
			"version" : 
			{
				"major" : 2,
				"minor" : 5
			}
		},
		{
			"jsonFile" : "cache-v2-4d42b8acee52bb79cb44.json",
			"kind" : "cache",
			"version" : 
			{
				"major" : 2,
				"minor" : 0
			}
		},
		{
			"jsonFile" : "cmakeFiles-v1-182fd3ac26097ecfc019.json",
			"kind" : "cmakeFiles",
			"version" : 
			{
				"major" : 1,
				"minor" : 0
			}
		},
		{
			"jsonFile" : "toolchains-v1-614d4e0c51b4215deae3.json",
			"kind" : "toolchains",
			"version" : 
			{
				"major" : 1,
				"minor" : 0
			}
		}
	],
	"reply" : 
	{
		"cache-v2" : 
		{
			"jsonFile" : "cache-v2-4d42b8acee52bb79cb44.json",
			"kind" : "cache",
			"version" : 
			{
				"major" : 2,
				"minor" : 0
			}
		},
		"cmakeFiles-v1" : 
		{
			"jsonFile" : "cmakeFiles-v1-182fd3ac26097ecfc019.json",
			"kind" : "cmakeFiles",
			"version" : 
			{
				"major" : 1,
				"minor" : 0
			}
		},
		"codemodel-v2" : 
		{
			"jsonFile" : "codemodel-v2-656fd20f3c3bde010993.json",
			"kind" : "codemodel",
			"version" : 
			{
				"major" : 2,
				"minor" : 5
			}
		},
		"toolchains-v1" : 
		{
			"jsonFile" : "toolchains-v1-614d4e0c51b4215deae3.json",
			"kind" : "toolchains",
			"version" : 
			{
				"major" : 1,
				"minor" : 0
			}
		}
	}
}
